redcap_client/__init__.py
redcap_client/models.py
redcap_integration-0.0.1.dist-info/METADATA
redcap_integration-0.0.1.dist-info/WHEEL
redcap_integration-0.0.1.dist-info/top_level.txt
redcap_integration-0.0.1.dist-info/RECORD
