Metadata-Version: 2.1
Name: redcap-integration
Version: 0.0.1
Summary: Redcap Integration
Home-page: https://github.com/IOMehran/redcap-integration
Author: Mehran Zolghadr
Author-email: mehran@keyleadhealth.com
License: UNKNOWN
Download-URL: https://github.com/IOMehran/redcap-integration/archive/refs/tags/v0.0.1.tar.gz
Project-URL: Bug Tracker, https://github.com/IOMehran/redcap-integration/issues
Platform: UNKNOWN
Classifier: Programming Language :: Python :: 3
Classifier: License :: OSI Approved :: MIT License
Classifier: Operating System :: OS Independent
Requires-Python: >=3.6
Requires-Dist: certifi (==2020.12.5)
Requires-Dist: chardet (==4.0.0)
Requires-Dist: idna (==2.10)
Requires-Dist: PyCap (==1.1.3)
Requires-Dist: python-dotenv (==0.17.1)
Requires-Dist: requests (==2.25.1)
Requires-Dist: semantic-version (==2.8.5)
Requires-Dist: urllib3 (==1.26.4)
